numato/__init__.py
numato/numato_controller.py
numato_control-1.0.0.dist-info/DESCRIPTION.rst
numato_control-1.0.0.dist-info/METADATA
numato_control-1.0.0.dist-info/RECORD
numato_control-1.0.0.dist-info/WHEEL
numato_control-1.0.0.dist-info/metadata.json
numato_control-1.0.0.dist-info/top_level.txt
