Metadata-Version: 2.0
Name: numato-control
Version: 1.0.0
Summary: Wrapper for Numato USB Control Boards
Home-page: http://github.com/angaza/numato_control
Author: Angaza
Author-email: devices@angaza.com
License: UNKNOWN
Platform: UNKNOWN
